[{"url": "//images.dmzj.com/l/%E6%B5%AA%E5%AE%A2%E8%A1%8C/%E6%B5%AA%E5%AE%A2%E8%A1%8C_%E7%AC%AC225%E8%AF%9D/%E6%B5%AA%E5%AE%A2%E8%A1%8C_%E6%B5%AA%E4%BA%BA%E5%89%91%E5%AE%A2_CH225_0001.jpg", "name": "001.jpg"}, {"url": "//images.dmzj.com/l/%E6%B5%AA%E5%AE%A2%E8%A1%8C/%E6%B5%AA%E5%AE%A2%E8%A1%8C_%E7%AC%AC225%E8%AF%9D/%E6%B5%AA%E5%AE%A2%E8%A1%8C_%E6%B5%AA%E4%BA%BA%E5%89%91%E5%AE%A2_CH225_0002.jpg", "name": "002.jpg"}, {"url": "//images.dmzj.com/l/%E6%B5%AA%E5%AE%A2%E8%A1%8C/%E6%B5%AA%E5%AE%A2%E8%A1%8C_%E7%AC%AC225%E8%AF%9D/%E6%B5%AA%E5%AE%A2%E8%A1%8C_%E6%B5%AA%E4%BA%BA%E5%89%91%E5%AE%A2_CH225_0003.jpg", "name": "003.jpg"}, {"url": "//images.dmzj.com/l/%E6%B5%AA%E5%AE%A2%E8%A1%8C/%E6%B5%AA%E5%AE%A2%E8%A1%8C_%E7%AC%AC225%E8%AF%9D/%E6%B5%AA%E5%AE%A2%E8%A1%8C_%E6%B5%AA%E4%BA%BA%E5%89%91%E5%AE%A2_CH225_0004.jpg", "name": "004.jpg"}, {"url": "//images.dmzj.com/l/%E6%B5%AA%E5%AE%A2%E8%A1%8C/%E6%B5%AA%E5%AE%A2%E8%A1%8C_%E7%AC%AC225%E8%AF%9D/%E6%B5%AA%E5%AE%A2%E8%A1%8C_%E6%B5%AA%E4%BA%BA%E5%89%91%E5%AE%A2_CH225_0005.png", "name": "005.png"}, {"url": "//images.dmzj.com/l/%E6%B5%AA%E5%AE%A2%E8%A1%8C/%E6%B5%AA%E5%AE%A2%E8%A1%8C_%E7%AC%AC225%E8%AF%9D/%E6%B5%AA%E5%AE%A2%E8%A1%8C_%E6%B5%AA%E4%BA%BA%E5%89%91%E5%AE%A2_CH225_0006.png", "name": "006.png"}, {"url": "//images.dmzj.com/l/%E6%B5%AA%E5%AE%A2%E8%A1%8C/%E6%B5%AA%E5%AE%A2%E8%A1%8C_%E7%AC%AC225%E8%AF%9D/%E6%B5%AA%E5%AE%A2%E8%A1%8C_%E6%B5%AA%E4%BA%BA%E5%89%91%E5%AE%A2_CH225_0007.png", "name": "007.png"}, {"url": "//images.dmzj.com/l/%E6%B5%AA%E5%AE%A2%E8%A1%8C/%E6%B5%AA%E5%AE%A2%E8%A1%8C_%E7%AC%AC225%E8%AF%9D/%E6%B5%AA%E5%AE%A2%E8%A1%8C_%E6%B5%AA%E4%BA%BA%E5%89%91%E5%AE%A2_CH225_0008.png", "name": "008.png"}, {"url": "//images.dmzj.com/l/%E6%B5%AA%E5%AE%A2%E8%A1%8C/%E6%B5%AA%E5%AE%A2%E8%A1%8C_%E7%AC%AC225%E8%AF%9D/%E6%B5%AA%E5%AE%A2%E8%A1%8C_%E6%B5%AA%E4%BA%BA%E5%89%91%E5%AE%A2_CH225_0009.png", "name": "009.png"}, {"url": "//images.dmzj.com/l/%E6%B5%AA%E5%AE%A2%E8%A1%8C/%E6%B5%AA%E5%AE%A2%E8%A1%8C_%E7%AC%AC225%E8%AF%9D/%E6%B5%AA%E5%AE%A2%E8%A1%8C_%E6%B5%AA%E4%BA%BA%E5%89%91%E5%AE%A2_CH225_0010.png", "name": "010.png"}, {"url": "//images.dmzj.com/l/%E6%B5%AA%E5%AE%A2%E8%A1%8C/%E6%B5%AA%E5%AE%A2%E8%A1%8C_%E7%AC%AC225%E8%AF%9D/%E6%B5%AA%E5%AE%A2%E8%A1%8C_%E6%B5%AA%E4%BA%BA%E5%89%91%E5%AE%A2_CH225_0011.png", "name": "011.png"}, {"url": "//images.dmzj.com/l/%E6%B5%AA%E5%AE%A2%E8%A1%8C/%E6%B5%AA%E5%AE%A2%E8%A1%8C_%E7%AC%AC225%E8%AF%9D/%E6%B5%AA%E5%AE%A2%E8%A1%8C_%E6%B5%AA%E4%BA%BA%E5%89%91%E5%AE%A2_CH225_0012.png", "name": "012.png"}, {"url": "//images.dmzj.com/l/%E6%B5%AA%E5%AE%A2%E8%A1%8C/%E6%B5%AA%E5%AE%A2%E8%A1%8C_%E7%AC%AC225%E8%AF%9D/%E6%B5%AA%E5%AE%A2%E8%A1%8C_%E6%B5%AA%E4%BA%BA%E5%89%91%E5%AE%A2_CH225_0013.png", "name": "013.png"}, {"url": "//images.dmzj.com/l/%E6%B5%AA%E5%AE%A2%E8%A1%8C/%E6%B5%AA%E5%AE%A2%E8%A1%8C_%E7%AC%AC225%E8%AF%9D/%E6%B5%AA%E5%AE%A2%E8%A1%8C_%E6%B5%AA%E4%BA%BA%E5%89%91%E5%AE%A2_CH225_0014.png", "name": "014.png"}, {"url": "//images.dmzj.com/l/%E6%B5%AA%E5%AE%A2%E8%A1%8C/%E6%B5%AA%E5%AE%A2%E8%A1%8C_%E7%AC%AC225%E8%AF%9D/%E6%B5%AA%E5%AE%A2%E8%A1%8C_%E6%B5%AA%E4%BA%BA%E5%89%91%E5%AE%A2_CH225_0015.png", "name": "015.png"}, {"url": "//images.dmzj.com/l/%E6%B5%AA%E5%AE%A2%E8%A1%8C/%E6%B5%AA%E5%AE%A2%E8%A1%8C_%E7%AC%AC225%E8%AF%9D/%E6%B5%AA%E5%AE%A2%E8%A1%8C_%E6%B5%AA%E4%BA%BA%E5%89%91%E5%AE%A2_CH225_0016.png", "name": "016.png"}, {"url": "//images.dmzj.com/l/%E6%B5%AA%E5%AE%A2%E8%A1%8C/%E6%B5%AA%E5%AE%A2%E8%A1%8C_%E7%AC%AC225%E8%AF%9D/%E6%B5%AA%E5%AE%A2%E8%A1%8C_%E6%B5%AA%E4%BA%BA%E5%89%91%E5%AE%A2_CH225_0017.png", "name": "017.png"}, {"url": "//images.dmzj.com/l/%E6%B5%AA%E5%AE%A2%E8%A1%8C/%E6%B5%AA%E5%AE%A2%E8%A1%8C_%E7%AC%AC225%E8%AF%9D/%E6%B5%AA%E5%AE%A2%E8%A1%8C_%E6%B5%AA%E4%BA%BA%E5%89%91%E5%AE%A2_CH225_0018.png", "name": "018.png"}, {"url": "//images.dmzj.com/l/%E6%B5%AA%E5%AE%A2%E8%A1%8C/%E6%B5%AA%E5%AE%A2%E8%A1%8C_%E7%AC%AC225%E8%AF%9D/%E6%B5%AA%E5%AE%A2%E8%A1%8C_%E6%B5%AA%E4%BA%BA%E5%89%91%E5%AE%A2_CH225_0019.png", "name": "019.png"}, {"url": "//images.dmzj.com/l/%E6%B5%AA%E5%AE%A2%E8%A1%8C/%E6%B5%AA%E5%AE%A2%E8%A1%8C_%E7%AC%AC225%E8%AF%9D/%E6%B5%AA%E5%AE%A2%E8%A1%8C_%E6%B5%AA%E4%BA%BA%E5%89%91%E5%AE%A2_CH225_0020.png", "name": "020.png"}, {"url": "//images.dmzj.com/l/%E6%B5%AA%E5%AE%A2%E8%A1%8C/%E6%B5%AA%E5%AE%A2%E8%A1%8C_%E7%AC%AC225%E8%AF%9D/%E6%B5%AA%E5%AE%A2%E8%A1%8C_%E6%B5%AA%E4%BA%BA%E5%89%91%E5%AE%A2_CH225_0021.png", "name": "021.png"}, {"url": "//images.dmzj.com/l/%E6%B5%AA%E5%AE%A2%E8%A1%8C/%E6%B5%AA%E5%AE%A2%E8%A1%8C_%E7%AC%AC225%E8%AF%9D/%E6%B5%AA%E5%AE%A2%E8%A1%8C_%E6%B5%AA%E4%BA%BA%E5%89%91%E5%AE%A2_CH225_0022.png", "name": "022.png"}]